{"singlePage": [], "startSite": "", "filingNum": "", "onePageListNum": 15, "commentLabelColor": "#006b75", "yearColorList": ["#bc4c00", "#0969da", "#1f883d", "#A333D0"], "i18n": "CN", "themeMode": "manual", "dayTheme": "light", "nightTheme": "dark", "urlMode": "pinyin", "script": "", "style": "", "head": "", "indexScript": "", "indexStyle": "", "bottomText": "", "showPostSource": 1, "iconList": {}, "UTC": 8, "rssSplit": "sentence", "exlink": {}, "needComment": 1, "allHead": "", "title": "Vekolyram\u306eBlog", "subTitle": "Vekolyram\u7684\u5c0f\u535a\u5ba2~", "avatarUrl": "https://avatars.githubusercontent.com/u/176578753?v=4", "GMEEK_VERSION": "last", "postListJson": {"P2": {"htmlDir": "docs/post/di-yi-ci-shi-yong-gmeek-bu-shu-bo-ke.html", "labels": ["documentation"], "postTitle": "\u7b2c\u4e00\u6b21\u4f7f\u7528gmeek\u90e8\u7f72\u535a\u5ba2", "postUrl": "post/di-yi-ci-shi-yong-gmeek-bu-shu-bo-ke.html", "postSourceUrl": "https://github.com/vekolyram/vekolyram.github.io/issues/2", "commentNum": 0, "wordCount": 6, "description": "**\u6d4b\u8bd5**\u3002", "top": 0, "createdAt": 1722436195, "style": "", "script": "", "head": "", "ogImage": "https://avatars.githubusercontent.com/u/176578753?v=4", "createdDate": "2024-07-31", "dateLabelColor": "#bc4c00"}, "P6": {"htmlDir": "docs/post/blog.html", "labels": ["bug"], "postTitle": "blog", "postUrl": "post/blog.html", "postSourceUrl": "https://github.com/vekolyram/vekolyram.github.io/issues/6", "commentNum": 0, "wordCount": 14, "description": "\u8c28\u4ee5\u6b64blog\u505a\u6211\u7684\u671f\u672b\u4f5c\u4e1a\u3002", "top": 0, "createdAt": 1722493104, "style": "", "script": "", "head": "", "ogImage": "https://avatars.githubusercontent.com/u/176578753?v=4", "createdDate": "2024-08-01", "dateLabelColor": "#bc4c00"}, "P10": {"htmlDir": "docs/post/fksw.html", "labels": ["duplicate"], "postTitle": "fksw", "postUrl": "post/fksw.html", "postSourceUrl": "https://github.com/vekolyram/vekolyram.github.io/issues/10", "commentNum": 0, "wordCount": 87, "description": "https://lsxad.lanzouj.com/izO5T2hl0z0b\r\nhttps://lsxad.lanzoux.com/izO5T2hl0z0b\r\n\u5bc6\u7801:64s7\u3002", "top": 0, "createdAt": 1733663489, "style": "", "script": "", "head": "", "ogImage": "https://avatars.githubusercontent.com/u/176578753?v=4", "createdDate": "2024-12-08", "dateLabelColor": "#bc4c00"}, "P11": {"htmlDir": "docs/post/FuConSeewo.html", "labels": ["duplicate"], "postTitle": "FuConSeewo", "postUrl": "post/FuConSeewo.html", "postSourceUrl": "https://github.com/vekolyram/vekolyram.github.io/issues/11", "commentNum": 0, "wordCount": 122, "description": "[FuCon.zip](https://github.com/user-attachments/files/18141141/FuCon.zip)\r\nhttps://lsxad.lanzouu.com/i0R7N2i7v2ri\r\n\u5bc6\u7801:e2cs\u3002", "top": 0, "createdAt": 1734278729, "style": "", "script": "", "head": "", "ogImage": "https://avatars.githubusercontent.com/u/176578753?v=4", "createdDate": "2024-12-16", "dateLabelColor": "#bc4c00"}}, "singeListJson": {}, "labelColorDict": {"bug": "#d73a4a", "documentation": "#0075ca", "duplicate": "#cfd3d7", "enhancement": "#a2eeef", "good first issue": "#7057ff", "help wanted": "#008672", "invalid": "#e4e669", "question": "#d876e3", "wontfix": "#ffffff"}, "displayTitle": "Vekolyram\u306eBlog", "faviconUrl": "https://avatars.githubusercontent.com/u/176578753?v=4", "ogImage": "https://avatars.githubusercontent.com/u/176578753?v=4", "primerCSS": "<link href='https://mirrors.sustech.edu.cn/cdnjs/ajax/libs/Primer/21.0.7/primer.css' rel='stylesheet' />", "homeUrl": "https://vekolyram.github.io", "prevUrl": "disabled", "nextUrl": "disabled"}